jen/__init__.py
jen/main_cli.py
cp_jen-2024.0.0.dist-info/entry_points.txt
cp_jen-2024.0.0.dist-info/LICENSE
cp_jen-2024.0.0.dist-info/WHEEL
cp_jen-2024.0.0.dist-info/METADATA
cp_jen-2024.0.0.dist-info/RECORD
