Metadata-Version: 2.1
Name: cp-jen
Version: 2024.0.0
Summary: Configurable test case generator for competitive programming.
Keywords: jen,cp-jen,Competitive Programming,Test Generator,Codeforces,Atcoder
Requires-Python: >= 3.11
Project-URL: Home, https://github.com/FaresBadrCA/cp-jen
